{
  "variables": {
    "memory": "4096",
    "host_name": "nca4010",
    "host_switch": "{{ env `HOST_SWITCH` }}",
    "github_user": "{{ env `GITHUB_USER` }}",
    "github_token": "{{ env `GITHUB_TOKEN` }}"
  },
  "builders": [
    {
      "vm_name": "nca4010",

      "type": "qemu",
      "format": "qcow2",

      "disk_image": true,
      "iso_url": "boxtemp/7/box.img",
      "iso_checksum_type": "none",
      "output_directory": "output-qemu",

      "http_directory": "http",
      "headless": true,

      "ssh_username": "vagrant",
      "ssh_password": "vagrant",
      "ssh_private_key_file": "boxtemp/7/vagrant.key",

      "ssh_wait_timeout": "10m",
      "shutdown_command": "echo 'vagrant' | sudo -S shutdown -P now",
      "qemuargs": [
        [ "-m", "{{ user `memory` }}" ],
        [ "-device", "pci-bridge,id=pbr0,bus=pci.0,chassis_nr=1" ],
        [ "-netdev", "user,id=net0,hostfwd=tcp::{{ .SSHHostPort }}-:22,net=10.0.2.0/24" ],
        [ "-device", "virtio-net,netdev=net0,mac=52:56:01:00:01:00,multifunction=on,bus=pbr0,addr=1.0" ],
        [ "-device", "virtio-net-pci,mac=52:56:01:00:01:01,multifunction=on,bus=pbr0,addr=1.1" ],
        [ "-device", "virtio-net-pci,mac=52:56:01:00:01:02,multifunction=on,bus=pbr0,addr=1.2" ],
        [ "-device", "virtio-net-pci,mac=52:56:01:00:01:03,multifunction=on,bus=pbr0,addr=1.3" ],
        [ "-device", "virtio-net-pci,mac=52:56:01:00:01:04,multifunction=on,bus=pbr0,addr=1.4" ],
        [ "-device", "virtio-net-pci,mac=52:56:01:00:01:05,multifunction=on,bus=pbr0,addr=1.5" ],
        [ "-device", "virtio-net-pci,mac=52:56:01:00:01:06,multifunction=on,bus=pbr0,addr=1.6" ],
        [ "-device", "virtio-net-pci,mac=52:56:01:00:01:07,multifunction=on,bus=pbr0,addr=1.7" ],
        [ "-device", "virtio-net-pci,mac=52:56:01:00:01:08,multifunction=on,bus=pbr0,addr=2.0" ],
        [ "-device", "virtio-net-pci,mac=52:56:01:00:01:09,multifunction=on,bus=pbr0,addr=2.1" ],
        [ "-device", "virtio-net-pci,mac=52:56:01:00:01:0a,multifunction=on,bus=pbr0,addr=2.2" ],
        [ "-device", "virtio-net-pci,mac=52:56:01:00:01:0b,multifunction=on,bus=pbr0,addr=2.3" ],
        [ "-device", "virtio-net-pci,mac=52:56:01:00:01:0c,multifunction=on,bus=pbr0,addr=2.4" ],
        [ "-device", "virtio-net-pci,mac=52:56:01:00:01:0d,multifunction=on,bus=pbr0,addr=2.5" ],
        [ "-device", "virtio-net-pci,mac=52:56:01:00:01:0e,multifunction=on,bus=pbr0,addr=2.6" ],
        [ "-device", "virtio-net-pci,mac=52:56:01:00:01:0f,multifunction=on,bus=pbr0,addr=2.7" ],
        [ "-device", "virtio-net-pci,mac=52:56:01:00:01:10,multifunction=on,bus=pbr0,addr=3.0" ],
        [ "-device", "virtio-net-pci,mac=52:56:01:00:01:11,multifunction=on,bus=pbr0,addr=3.1" ],
        [ "-device", "virtio-net-pci,mac=52:56:01:00:01:12,multifunction=on,bus=pbr0,addr=3.2" ]
      ]
    }
  ],
  "provisioners": [
    {
      "type": "file",
      "source": "fastestmirror.conf",
      "destination": "/tmp/fastestmirror.conf"
    },
    {
      "type": "shell",
      "execute_command": "chmod +x {{ .Path }}; echo 'vagrant' | {{ .Vars }} sudo -S -E sh -eux '{{ .Path }}'",
      "inline": [
        "cp /tmp/fastestmirror.conf /etc/yum/pluginconf.d/fastestmirror.conf",
        "sed -i -e 's!^PasswordAuthentication no!PasswordAuthentication yes!' /etc/ssh/sshd_config",
        "nmcli connection modify 'System eth0' connection.interface-name eth0 connection.id eth0",
        "nmcli connection modify 'Wired connection 1' connection.interface-name if1 connection.id if1",
        "nmcli connection modify 'Wired connection 2' connection.interface-name if2 connection.id if2",
        "nmcli connection modify 'Wired connection 3' connection.interface-name if3 connection.id if3",
        "nmcli connection modify 'Wired connection 4' connection.interface-name if4 connection.id if4",
        "nmcli connection modify 'Wired connection 5' connection.interface-name if5 connection.id if5",
        "nmcli connection modify 'Wired connection 6' connection.interface-name if6 connection.id if6",
        "nmcli connection modify 'Wired connection 7' connection.interface-name if7 connection.id if7",
        "nmcli connection modify 'Wired connection 8' connection.interface-name if8 connection.id if8",
        "nmcli connection modify 'Wired connection 9' connection.interface-name if9 connection.id if9",
        "nmcli connection modify 'Wired connection 10' connection.interface-name if10 connection.id if10",
        "nmcli connection modify 'Wired connection 11' connection.interface-name if11 connection.id if11",
        "nmcli connection modify 'Wired connection 12' connection.interface-name if12 connection.id if12",
        "nmcli connection modify 'Wired connection 13' connection.interface-name if13 connection.id if13",
        "nmcli connection modify 'Wired connection 14' connection.interface-name if14 connection.id if14",
        "nmcli connection modify 'Wired connection 15' connection.interface-name if15 connection.id if15",
        "nmcli connection modify 'Wired connection 16' connection.interface-name if16 connection.id if16",
        "nmcli connection modify 'Wired connection 17' connection.interface-name if17 connection.id if17",
        "nmcli connection modify 'Wired connection 18' connection.interface-name if18 connection.id if18",
        "systemctl restart NetworkManager",
        "nmcli connection modify eth0 ipv4.dns 8.8.8.8",
        "nmcli connection modify eth0 ipv4.ignore-auto-dns yes",
        "sudo hostnamectl set-hostname '{{ user `host_name` }}'",
        "yum -y install pciutils",
        "yum clean all"
      ]
    },
    {
      "destination": "/var/tmp/",
      "source": "packer_cache/tree.tar",
      "type": "file"
    },
    {
      "type": "shell",
      "execute_command": "chmod +x {{ .Path }}; echo 'vagrant' | {{ .Vars }} sudo -S -E sh -eux '{{ .Path }}'",
      "inline": [
        "cd /var/tmp/",
        "tar xf tree.tar",
        "cd lanner"
      ]
    }
  ]
}
